xtractr_package/__init__.py
xtractr_package/xtractor.py
xtractr-0.0.1.dist-info/LICENSE
xtractr-0.0.1.dist-info/METADATA
xtractr-0.0.1.dist-info/WHEEL
xtractr-0.0.1.dist-info/top_level.txt
xtractr-0.0.1.dist-info/RECORD
