Metadata-Version: 2.1
Name: xtractr
Version: 0.0.1
Summary: A mechanism to improve extraction
Home-page: https://github.com/ncaldwell17/xTractr
Author: Noah Caldwell-Gatsos
Author-email: ncg17developer@gmail.com
License: UNKNOWN
Platform: UNKNOWN
Classifier: Programming Language :: Python :: 3
Classifier: License :: OSI Approved :: MIT License
Classifier: Operating System :: OS Independent
Requires-Python: >=3.6
